aic_sdk/__init__.py
aic_sdk/__init__.pyi
aic_sdk/aic_sdk.cpython-313-darwin.so
aic_sdk/py.typed
aic_sdk-2.0.1.dist-info/METADATA
aic_sdk-2.0.1.dist-info/WHEEL
aic_sdk-2.0.1.dist-info/licenses/LICENSE
aic_sdk-2.0.1.dist-info/licenses/LICENSE.AIC-SDK
aic_sdk.pyi
aic_sdk-2.0.1.dist-info/RECORD
