Metadata-Version: 2.4
Name: aic-sdk
Version: 2.0.1
Classifier: Development Status :: 5 - Production/Stable
Classifier: License :: OSI Approved :: Apache Software License
Classifier: Operating System :: MacOS
Classifier: Operating System :: Microsoft :: Windows
Classifier: Operating System :: POSIX :: Linux
Classifier: Programming Language :: Python :: 3
Classifier: Programming Language :: Python :: 3.10
Classifier: Programming Language :: Python :: 3.11
Classifier: Programming Language :: Python :: 3.12
Classifier: Programming Language :: Python :: 3.13
Classifier: Programming Language :: Python :: 3.14
Classifier: Programming Language :: Rust
Classifier: Topic :: Multimedia :: Sound/Audio :: Speech
Requires-Dist: numpy>=2.0.2
Requires-Dist: pytest-asyncio>=0.21.0 ; extra == 'dev'
Requires-Dist: pytest>=7.0 ; extra == 'dev'
Provides-Extra: dev
License-File: LICENSE
License-File: LICENSE.AIC-SDK
Summary: Python bindings for ai-coustics SDK
Author-email: ai-coustics GmbH <info@ai-coustics.com>
Requires-Python: >=3.10
